omemdb/__init__.py
omemdb/conf.py
omemdb/db.py
omemdb/dynamic_fields_schema.py
omemdb/excel.py
omemdb/marsh_validator.py
omemdb/multi_table_queryset.py
omemdb/oerrors_omemdb.py
omemdb/queryset.py
omemdb/record.py
omemdb/record_link.py
omemdb/records_container.py
omemdb/relations_manager.py
omemdb/table.py
omemdb/util.py
omemdb/version.py
omemdb/omemdb_fields/__init__.py
omemdb/omemdb_fields/api.py
omemdb/omemdb_fields/base_link_field.py
omemdb/omemdb_fields/base_linkable_field.py
omemdb/omemdb_fields/flexible_dict_field.py
omemdb/omemdb_fields/link_field.py
omemdb/omemdb_fields/tuple_link_field.py
omemdb/packages/__init__.py
omemdb/packages/oversion.py
omemdb/packages/oerrors/__init__.py
omemdb/packages/oerrors/base_errors.py
omemdb/packages/oerrors/conf.py
omemdb/packages/oerrors/marsh.py
omemdb/packages/oerrors/oexception.py
omemdb/packages/oerrors/oexception_collection.py
omemdb/packages/oerrors/rest_framework.py
omemdb/packages/oerrors/unauthorized_errors.py
omemdb/packages/oerrors/validation_errors.py
omemdb/packages/omarsh/__init__.py
omemdb/packages/omarsh/decorators.py
omemdb/packages/omarsh/fields.py
omemdb/packages/omarsh/no_validation_deserializer.py
omemdb/packages/omarsh/ofields.py
omemdb/packages/omarsh/ovalidate.py
omemdb/packages/omarsh/schema.py
omemdb/packages/omarsh/validate.py
tests/__init__.py
tests/app_building.py
tests/app_dynamic_id.py
tests/app_err.py
tests/app_fields.py
tests/app_simple.py
tests/test_commitments.py
tests/test_fields.py
tests/test_omemdb.py
tests/packages/__init__.py
tests/packages/tests_oerrors/__init__.py
tests/packages/tests_oerrors/test_marsh.py
tests/packages/tests_omarsh/__init__.py
omemdb-3.0.2.dist-info/LICENSE.txt
omemdb-3.0.2.dist-info/METADATA
omemdb-3.0.2.dist-info/WHEEL
omemdb-3.0.2.dist-info/top_level.txt
omemdb-3.0.2.dist-info/RECORD
