Metadata-Version: 2.1
Name: omemdb
Version: 3.0.2
Home-page: https://github.com/openergy/omemdb
Author: Openergy team
Author-email: contact@openergy.fr
Classifier: Programming Language :: Python
Classifier: Development Status :: 5 - Production/Stable
Classifier: Intended Audience :: Science/Research
Classifier: Natural Language :: French
Classifier: Operating System :: POSIX :: Linux
Classifier: Programming Language :: Python :: 3.8
Classifier: Programming Language :: Python :: 3.9
Classifier: Programming Language :: Python :: 3.10
Classifier: Programming Language :: Python :: 3.11
Classifier: Programming Language :: Python :: 3.12
Classifier: Topic :: Scientific/Engineering :: Physics
License-File: LICENSE.txt
Requires-Dist: numpy <2.0,>=1.14.2
Requires-Dist: pandas <3.0,>=2.0.0
Requires-Dist: marshmallow <4.0,>=3.0.0
